{
  "language": "Espa침ol",
  "login": {
    "label": "Iniciar sesi칩n",
    "butttonTooltip": "Presiona 'Enter' o haz clic para iniciar sesi칩n. Aseg칰rate de cumplir todas las validaciones requeridas y tener una cuenta registrada y confirmada."
  },
  "slogan": "Hecho con 仇벒잺 y 游 por un mejor futuro",
  "changeLanguage": "cambiar idioma",
  "emailLabel": {
    "label": "Correo electr칩nico",
    "tooltip": "Por favor ingresa un correo electr칩nico v치lido. El correo debe estar en la lista de correos v치lidos.",
    "hint": "Pista: Aseg칰rate de ingresar un correo electr칩nico v치lido. Generalmente, son los correos institucionales."
  },
  "passwordLabel": {
    "label": "Contrase침a",
    "tooltip": "Por favor ingresa una contrase침a v치lida. La contrase침a debe tener al menos 8 caracteres. En caso de olvidarla, puedes solicitar la recuperaci칩n de la misma.",
    "hint": "Pista: Aseg칰rate de ingresar una contrase침a segura de al menos 8 caracteres."
  },
  "forgotPassword": "쮿as olvidado tu contrase침a? Haz clic aqu칤 para recuperarla."
}
